nlp_feature_extractors/__init__.py
nlp_feature_extractors/attribute_extractors.py
nlp_feature_extractors/data/__init__.py
nlp_feature_extractors/data/female-words.txt
nlp_feature_extractors/data/male-words.txt
nlp_feature_extractors/data/neutral-words.txt
nlp_feature_extractors-0.1.0.dist-info/METADATA
nlp_feature_extractors-0.1.0.dist-info/WHEEL
nlp_feature_extractors-0.1.0.dist-info/top_level.txt
nlp_feature_extractors-0.1.0.dist-info/RECORD
