Metadata-Version: 2.1
Name: nlp-feature-extractors
Version: 0.1.0
Summary: NLP Feature Extractors
Home-page: https://github.com/microsoft/responsible-ai-widgets
Author: 
Author-email: raiwidgets-maintain@microsoft.com
Classifier: Programming Language :: Python :: 3
Classifier: Programming Language :: Python :: 3.6
Classifier: Programming Language :: Python :: 3.7
Classifier: Programming Language :: Python :: 3.8
Classifier: Programming Language :: Python :: 3.9
Classifier: License :: OSI Approved :: MIT License
Classifier: Operating System :: OS Independent
Classifier: Development Status :: 3 - Alpha
Requires-Dist: datasets
Requires-Dist: gender-guesser (>=0.4.0)
Requires-Dist: negspacy (>=1.0.0)
Requires-Dist: numpy (>=1.17.2)
Requires-Dist: sentencepiece
Requires-Dist: spacy
Requires-Dist: tqdm
Requires-Dist: raiutils (>=0.2.0)
